subsonar/__init__.py
subsonar/main.py
subsonar/sonar_metric.py
subsonar/srt_reader.py
SubSONAR-1.0.dist-info/LICENSE
SubSONAR-1.0.dist-info/METADATA
SubSONAR-1.0.dist-info/WHEEL
SubSONAR-1.0.dist-info/entry_points.txt
SubSONAR-1.0.dist-info/top_level.txt
SubSONAR-1.0.dist-info/RECORD
