Metadata-Version: 2.1
Name: SubSONAR
Version: 1.0
Summary: Evaluate the quality of SRT files using the multilingual multimodal SONAR model.
Author-email: Marco Gaido <mgaido@fbk.eu>
Project-URL: Homepage, https://github.com/hlt-mt/subsonar
Project-URL: Bug Tracker, https://github.com/hlt-mt/subsonar/issues
Classifier: Programming Language :: Python :: 3
Classifier: License :: OSI Approved :: Apache Software License
Classifier: Operating System :: OS Independent
Classifier: Topic :: Scientific/Engineering :: Artificial Intelligence
Requires-Python: >=3.8
License-File: LICENSE
Requires-Dist: sonar-space
Requires-Dist: argparse
Requires-Dist: srt
Requires-Dist: torchaudio
Requires-Dist: numpy >=1.21
Requires-Dist: torch >=1.9
Requires-Dist: tqdm
Requires-Dist: fairseq2
Provides-Extra: dev
Requires-Dist: flake8 ; extra == 'dev'
Provides-Extra: release
Requires-Dist: build ; extra == 'release'
Requires-Dist: twine ; extra == 'release'
Requires-Dist: sphinx ; extra == 'release'
Requires-Dist: sphinx-rtd-theme ; extra == 'release'
